<?xml version="1.0" encoding="UTF-8"?>
<definitions xmlns="http://www.omg.org/spec/BPMN/20100524/MODEL"
             xmlns:xsi="http://www.w3.org/2001/XMLSchema-instance"
             xmlns:bpmndi="http://www.omg.org/spec/BPMN/20100524/DI"
             xmlns:omgdc="http://www.omg.org/spec/DD/20100524/DC"
             xmlns:omgdi="http://www.omg.org/spec/DD/20100524/DI"
             xmlns:flowable="http://flowable.org/bpmn"
             targetNamespace="http://www.flowable.org/processdef">
    <process id="feeApplyProcess" name="资金申请审批流程" isExecutable="true">
        <userTask id="submitForm" name="资金申请" flowable:assignee="${taskUserId}"></userTask>
        <exclusiveGateway id="decideSubmit" name="提交OR取消"></exclusiveGateway>
        <sequenceFlow id="flow3" sourceRef="submitForm" targetRef="decideSubmit"></sequenceFlow>
        <userTask id="finance_approve" name="审批(财务)" >
            <extensionElements>
                <flowable:taskListener event="create" class="com.tce.oa.core.common.handler.ApplyProcessTaskHandler"></flowable:taskListener>
            </extensionElements>
        </userTask>
        <startEvent id="reimburseStart" name="资金申请开始"></startEvent>
        <sequenceFlow id="flow11" sourceRef="reimburseStart" targetRef="submitForm"></sequenceFlow>
        <endEvent id="reimburseCancel" name="资金申请取消"></endEvent>
        <sequenceFlow id="flow12" name="撤回" sourceRef="decideSubmit" targetRef="reimburseCancel">
            <conditionExpression xsi:type="tFormalExpression"><![CDATA[${submitType == "驳回"}]]></conditionExpression>
        </sequenceFlow>
        <exclusiveGateway id="decideFinanceSubmit" name="财务审批校验"></exclusiveGateway>
        <sequenceFlow id="flow13" name="同意" sourceRef="finance_approve" targetRef="decideFinanceSubmit"></sequenceFlow>
        <userTask id="manager_approve" name="审批(总裁)">
            <extensionElements>
                <flowable:taskListener event="create" class="com.tce.oa.core.common.handler.ApplyProcessTaskHandler"></flowable:taskListener>
            </extensionElements>
        </userTask>
        <userTask id="deputyManager_approve" name="审批(副总裁)">
            <extensionElements>
                <flowable:taskListener event="create" class="com.tce.oa.core.common.handler.ApplyProcessTaskHandler"></flowable:taskListener>
            </extensionElements>
        </userTask>
        <sequenceFlow id="flow14" name="重庆申请" sourceRef="decideFinanceSubmit" targetRef="manager_approve">
            <extensionElements>
                <flowable:executionListener delegateExpression="${mailListener}"></flowable:executionListener>
            </extensionElements>
            <conditionExpression xsi:type="tFormalExpression"><![CDATA[${submitType == "同意" && (location == "cq" || location == "CQ") && (taskUser != "deputy" && taskUser != "manager")}]]></conditionExpression>
        </sequenceFlow>
        <sequenceFlow id="flow15" name="北京申请" sourceRef="decideFinanceSubmit" targetRef="deputyManager_approve">
            <extensionElements>
                <flowable:executionListener delegateExpression="${mailListener}"></flowable:executionListener>
            </extensionElements>
            <conditionExpression xsi:type="tFormalExpression"><![CDATA[${submitType == "同意" && (location == "bj" || location == "BJ") && (taskUser != "deputy" && taskUser != "manager")}]]></conditionExpression>
        </sequenceFlow>
        <endEvent id="finance_end" name="财务审批结束"></endEvent>
        <sequenceFlow id="flow28" sourceRef="decideFinanceSubmit" targetRef="finance_end">
            <extensionElements>
                <flowable:executionListener delegateExpression="${mailListener}"></flowable:executionListener>
            </extensionElements>
            <conditionExpression xsi:type="tFormalExpression"><![CDATA[${submitType == "同意" && (taskUser == "deputy" || taskUser == "manager")}]]></conditionExpression>
        </sequenceFlow>
        <exclusiveGateway id="decideSubManagerSubmit" name="副总裁审批校验"></exclusiveGateway>
        <sequenceFlow id="flow16" name="同意" sourceRef="deputyManager_approve" targetRef="decideSubManagerSubmit"></sequenceFlow>
        <sequenceFlow id="flow17" sourceRef="decideSubManagerSubmit" targetRef="manager_approve">
            <extensionElements>
                <flowable:executionListener delegateExpression="${mailListener}"></flowable:executionListener>
            </extensionElements>
            <conditionExpression xsi:type="tFormalExpression"><![CDATA[${submitType == "同意"}]]></conditionExpression>
        </sequenceFlow>
        <sequenceFlow id="flow19" name="不同意" sourceRef="decideFinanceSubmit" targetRef="submitForm">
            <conditionExpression xsi:type="tFormalExpression"><![CDATA[${submitType == "驳回"}]]></conditionExpression>
        </sequenceFlow>
        <exclusiveGateway id="decideManagerSubmit" name="总裁审批校验"></exclusiveGateway>
        <sequenceFlow id="flow20" name="同意" sourceRef="manager_approve" targetRef="decideManagerSubmit"></sequenceFlow>
        <endEvent id="reimburseEnd" name="结束"></endEvent>
        <sequenceFlow id="flow21" sourceRef="decideManagerSubmit" targetRef="reimburseEnd">
            <extensionElements>
                <flowable:executionListener delegateExpression="${mailListener}"></flowable:executionListener>
            </extensionElements>
            <conditionExpression xsi:type="tFormalExpression"><![CDATA[${submitType == "同意"}]]></conditionExpression>
        </sequenceFlow>
        <sequenceFlow id="flow22" name="不同意" sourceRef="decideSubManagerSubmit" targetRef="submitForm">
            <conditionExpression xsi:type="tFormalExpression"><![CDATA[${submitType == "驳回"}]]></conditionExpression>
        </sequenceFlow>
        <sequenceFlow id="flow23" name="不同意" sourceRef="decideManagerSubmit" targetRef="submitForm">
            <conditionExpression xsi:type="tFormalExpression"><![CDATA[${submitType == "驳回"}]]></conditionExpression>
        </sequenceFlow>
        <userTask id="leader_approve" name="审批(部门负责人)">
            <extensionElements>
                <flowable:taskListener event="create" class="com.tce.oa.core.common.handler.ApplyProcessTaskHandler"></flowable:taskListener>
            </extensionElements>
        </userTask>
        <sequenceFlow id="flow24" name="提交" sourceRef="decideSubmit" targetRef="leader_approve">
            <extensionElements>
                <flowable:executionListener delegateExpression="${mailListener}"></flowable:executionListener>
            </extensionElements>
            <conditionExpression xsi:type="tFormalExpression"><![CDATA[${submitType == "同意"}]]></conditionExpression>
        </sequenceFlow>
        <exclusiveGateway id="decideLeaderSubmit" name="部门负责人审批"></exclusiveGateway>
        <sequenceFlow id="flow25" sourceRef="leader_approve" targetRef="decideLeaderSubmit"></sequenceFlow>
        <sequenceFlow id="flow26" name="同意" sourceRef="decideLeaderSubmit" targetRef="finance_approve">
            <extensionElements>
                <flowable:executionListener delegateExpression="${mailListener}"></flowable:executionListener>
            </extensionElements>
            <conditionExpression xsi:type="tFormalExpression"><![CDATA[${submitType == "同意"}]]></conditionExpression>
        </sequenceFlow>
        <sequenceFlow id="flow27" name="不同意" sourceRef="decideLeaderSubmit" targetRef="submitForm">
            <conditionExpression xsi:type="tFormalExpression"><![CDATA[${submitType == "驳回"}]]></conditionExpression>
        </sequenceFlow>

    </process>
    <bpmndi:BPMNDiagram id="BPMNDiagram_feeApplyProcess">
        <bpmndi:BPMNPlane bpmnElement="feeApplyProcess" id="BPMNPlane_feeApplyProcess">
            <bpmndi:BPMNShape bpmnElement="submitForm" id="BPMNShape_submitForm">
                <omgdc:Bounds height="55.0" width="105.0" x="117.0" y="253.0"></omgdc:Bounds>
            </bpmndi:BPMNShape>
            <bpmndi:BPMNShape bpmnElement="decideSubmit" id="BPMNShape_decideSubmit">
                <omgdc:Bounds height="40.0" width="40.0" x="281.0" y="261.0"></omgdc:Bounds>
            </bpmndi:BPMNShape>
            <bpmndi:BPMNShape bpmnElement="finance_approve" id="BPMNShape_finance_approve">
                <omgdc:Bounds height="55.0" width="105.0" x="621.0" y="253.0"></omgdc:Bounds>
            </bpmndi:BPMNShape>
            <bpmndi:BPMNShape bpmnElement="reimburseStart" id="BPMNShape_reimburseStart">
                <omgdc:Bounds height="35.0" width="35.0" x="34.0" y="263.0"></omgdc:Bounds>
            </bpmndi:BPMNShape>
            <bpmndi:BPMNShape bpmnElement="reimburseCancel" id="BPMNShape_reimburseCancel">
                <omgdc:Bounds height="35.0" width="35.0" x="284.0" y="363.0"></omgdc:Bounds>
            </bpmndi:BPMNShape>
            <bpmndi:BPMNShape bpmnElement="decideFinanceSubmit" id="BPMNShape_decideFinanceSubmit">
                <omgdc:Bounds height="40.0" width="40.0" x="801.0" y="260.0"></omgdc:Bounds>
            </bpmndi:BPMNShape>
            <bpmndi:BPMNShape bpmnElement="manager_approve" id="BPMNShape_manager_approve">
                <omgdc:Bounds height="55.0" width="105.0" x="886.0" y="253.0"></omgdc:Bounds>
            </bpmndi:BPMNShape>
            <bpmndi:BPMNShape bpmnElement="deputyManager_approve" id="BPMNShape_deputyManager_approve">
                <omgdc:Bounds height="55.0" width="105.0" x="769.0" y="164.0"></omgdc:Bounds>
            </bpmndi:BPMNShape>
            <bpmndi:BPMNShape bpmnElement="decideSubManagerSubmit" id="BPMNShape_decideSubManagerSubmit">
                <omgdc:Bounds height="40.0" width="40.0" x="918.0" y="171.0"></omgdc:Bounds>
            </bpmndi:BPMNShape>
            <bpmndi:BPMNShape bpmnElement="decideManagerSubmit" id="BPMNShape_decideManagerSubmit">
                <omgdc:Bounds height="40.0" width="40.0" x="1036.0" y="261.0"></omgdc:Bounds>
            </bpmndi:BPMNShape>
            <bpmndi:BPMNShape bpmnElement="reimburseEnd" id="BPMNShape_reimburseEnd">
                <omgdc:Bounds height="35.0" width="35.0" x="1121.0" y="264.0"></omgdc:Bounds>
            </bpmndi:BPMNShape>
            <bpmndi:BPMNShape bpmnElement="leader_approve" id="BPMNShape_leader_approve">
                <omgdc:Bounds height="55.0" width="105.0" x="366.0" y="254.0"></omgdc:Bounds>
            </bpmndi:BPMNShape>
            <bpmndi:BPMNShape bpmnElement="decideLeaderSubmit" id="BPMNShape_decideLeaderSubmit">
                <omgdc:Bounds height="40.0" width="40.0" x="516.0" y="262.0"></omgdc:Bounds>
            </bpmndi:BPMNShape>
            <bpmndi:BPMNShape bpmnElement="finance_end" id="BPMNShape_finance_end">
                <omgdc:Bounds height="35.0" width="35.0" x="886.0" y="356.0"></omgdc:Bounds>
            </bpmndi:BPMNShape>
            <bpmndi:BPMNEdge bpmnElement="flow3" id="BPMNEdge_flow3">
                <omgdi:waypoint x="222.0" y="280.0"></omgdi:waypoint>
                <omgdi:waypoint x="281.0" y="281.0"></omgdi:waypoint>
            </bpmndi:BPMNEdge>
            <bpmndi:BPMNEdge bpmnElement="flow11" id="BPMNEdge_flow11">
                <omgdi:waypoint x="69.0" y="280.0"></omgdi:waypoint>
                <omgdi:waypoint x="117.0" y="280.0"></omgdi:waypoint>
            </bpmndi:BPMNEdge>
            <bpmndi:BPMNEdge bpmnElement="flow12" id="BPMNEdge_flow12">
                <omgdi:waypoint x="301.0" y="301.0"></omgdi:waypoint>
                <omgdi:waypoint x="301.0" y="363.0"></omgdi:waypoint>
                <bpmndi:BPMNLabel>
                    <omgdc:Bounds height="14.0" width="24.0" x="300.0" y="329.0"></omgdc:Bounds>
                </bpmndi:BPMNLabel>
            </bpmndi:BPMNEdge>
            <bpmndi:BPMNEdge bpmnElement="flow13" id="BPMNEdge_flow13">
                <omgdi:waypoint x="726.0" y="280.0"></omgdi:waypoint>
                <omgdi:waypoint x="801.0" y="280.0"></omgdi:waypoint>
                <bpmndi:BPMNLabel>
                    <omgdc:Bounds height="14.0" width="24.0" x="829.0" y="260.0"></omgdc:Bounds>
                </bpmndi:BPMNLabel>
            </bpmndi:BPMNEdge>
            <bpmndi:BPMNEdge bpmnElement="flow14" id="BPMNEdge_flow14">
                <omgdi:waypoint x="841.0" y="280.0"></omgdi:waypoint>
                <omgdi:waypoint x="886.0" y="280.0"></omgdi:waypoint>
                <bpmndi:BPMNLabel>
                    <omgdc:Bounds height="14.0" width="48.0" x="836.0" y="293.0"></omgdc:Bounds>
                </bpmndi:BPMNLabel>
            </bpmndi:BPMNEdge>
            <bpmndi:BPMNEdge bpmnElement="flow15" id="BPMNEdge_flow15">
                <omgdi:waypoint x="821.0" y="260.0"></omgdi:waypoint>
                <omgdi:waypoint x="821.0" y="219.0"></omgdi:waypoint>
                <bpmndi:BPMNLabel>
                    <omgdc:Bounds height="14.0" width="48.0" x="772.0" y="232.0"></omgdc:Bounds>
                </bpmndi:BPMNLabel>
            </bpmndi:BPMNEdge>
            <bpmndi:BPMNEdge bpmnElement="flow16" id="BPMNEdge_flow16">
                <omgdi:waypoint x="874.0" y="191.0"></omgdi:waypoint>
                <omgdi:waypoint x="918.0" y="191.0"></omgdi:waypoint>
                <bpmndi:BPMNLabel>
                    <omgdc:Bounds height="14.0" width="24.0" x="949.0" y="206.0"></omgdc:Bounds>
                </bpmndi:BPMNLabel>
            </bpmndi:BPMNEdge>
            <bpmndi:BPMNEdge bpmnElement="flow17" id="BPMNEdge_flow17">
                <omgdi:waypoint x="938.0" y="211.0"></omgdi:waypoint>
                <omgdi:waypoint x="938.0" y="253.0"></omgdi:waypoint>
            </bpmndi:BPMNEdge>
            <bpmndi:BPMNEdge bpmnElement="flow19" id="BPMNEdge_flow19">
                <omgdi:waypoint x="821.0" y="300.0"></omgdi:waypoint>
                <omgdi:waypoint x="821.0" y="455.0"></omgdi:waypoint>
                <omgdi:waypoint x="466.0" y="455.0"></omgdi:waypoint>
                <omgdi:waypoint x="169.0" y="455.0"></omgdi:waypoint>
                <omgdi:waypoint x="169.0" y="308.0"></omgdi:waypoint>
                <bpmndi:BPMNLabel>
                    <omgdc:Bounds height="14.0" width="36.0" x="774.0" y="429.0"></omgdc:Bounds>
                </bpmndi:BPMNLabel>
            </bpmndi:BPMNEdge>
            <bpmndi:BPMNEdge bpmnElement="flow20" id="BPMNEdge_flow20">
                <omgdi:waypoint x="991.0" y="280.0"></omgdi:waypoint>
                <omgdi:waypoint x="1036.0" y="281.0"></omgdi:waypoint>
                <bpmndi:BPMNLabel>
                    <omgdc:Bounds height="14.0" width="24.0" x="1075.0" y="287.0"></omgdc:Bounds>
                </bpmndi:BPMNLabel>
            </bpmndi:BPMNEdge>
            <bpmndi:BPMNEdge bpmnElement="flow21" id="BPMNEdge_flow21">
                <omgdi:waypoint x="1076.0" y="281.0"></omgdi:waypoint>
                <omgdi:waypoint x="1121.0" y="281.0"></omgdi:waypoint>
            </bpmndi:BPMNEdge>
            <bpmndi:BPMNEdge bpmnElement="flow22" id="BPMNEdge_flow22">
                <omgdi:waypoint x="938.0" y="171.0"></omgdi:waypoint>
                <omgdi:waypoint x="938.0" y="99.0"></omgdi:waypoint>
                <omgdi:waypoint x="169.0" y="99.0"></omgdi:waypoint>
                <omgdi:waypoint x="169.0" y="253.0"></omgdi:waypoint>
                <bpmndi:BPMNLabel>
                    <omgdc:Bounds height="14.0" width="36.0" x="898.0" y="78.0"></omgdc:Bounds>
                </bpmndi:BPMNLabel>
            </bpmndi:BPMNEdge>
            <bpmndi:BPMNEdge bpmnElement="flow23" id="BPMNEdge_flow23">
                <omgdi:waypoint x="1056.0" y="301.0"></omgdi:waypoint>
                <omgdi:waypoint x="1056.0" y="487.0"></omgdi:waypoint>
                <omgdi:waypoint x="617.0" y="487.0"></omgdi:waypoint>
                <omgdi:waypoint x="169.0" y="487.0"></omgdi:waypoint>
                <omgdi:waypoint x="169.0" y="308.0"></omgdi:waypoint>
                <bpmndi:BPMNLabel>
                    <omgdc:Bounds height="14.0" width="36.0" x="1001.0" y="466.0"></omgdc:Bounds>
                </bpmndi:BPMNLabel>
            </bpmndi:BPMNEdge>
            <bpmndi:BPMNEdge bpmnElement="flow24" id="BPMNEdge_flow24">
                <omgdi:waypoint x="321.0" y="281.0"></omgdi:waypoint>
                <omgdi:waypoint x="366.0" y="281.0"></omgdi:waypoint>
                <bpmndi:BPMNLabel>
                    <omgdc:Bounds height="14.0" width="24.0" x="321.0" y="281.0"></omgdc:Bounds>
                </bpmndi:BPMNLabel>
            </bpmndi:BPMNEdge>
            <bpmndi:BPMNEdge bpmnElement="flow25" id="BPMNEdge_flow25">
                <omgdi:waypoint x="471.0" y="281.0"></omgdi:waypoint>
                <omgdi:waypoint x="516.0" y="282.0"></omgdi:waypoint>
            </bpmndi:BPMNEdge>
            <bpmndi:BPMNEdge bpmnElement="flow26" id="BPMNEdge_flow26">
                <omgdi:waypoint x="556.0" y="282.0"></omgdi:waypoint>
                <omgdi:waypoint x="621.0" y="280.0"></omgdi:waypoint>
                <bpmndi:BPMNLabel>
                    <omgdc:Bounds height="14.0" width="24.0" x="556.0" y="282.0"></omgdc:Bounds>
                </bpmndi:BPMNLabel>
            </bpmndi:BPMNEdge>
            <bpmndi:BPMNEdge bpmnElement="flow27" id="BPMNEdge_flow27">
                <omgdi:waypoint x="536.0" y="302.0"></omgdi:waypoint>
                <omgdi:waypoint x="535.0" y="411.0"></omgdi:waypoint>
                <omgdi:waypoint x="376.0" y="411.0"></omgdi:waypoint>
                <omgdi:waypoint x="169.0" y="411.0"></omgdi:waypoint>
                <omgdi:waypoint x="169.0" y="308.0"></omgdi:waypoint>
                <bpmndi:BPMNLabel>
                    <omgdc:Bounds height="14.0" width="36.0" x="458.0" y="389.0"></omgdc:Bounds>
                </bpmndi:BPMNLabel>
            </bpmndi:BPMNEdge>
            <bpmndi:BPMNEdge bpmnElement="flow28" id="BPMNEdge_flow28">
                <omgdi:waypoint x="821.0" y="300.0"></omgdi:waypoint>
                <omgdi:waypoint x="903.0" y="356.0"></omgdi:waypoint>
            </bpmndi:BPMNEdge>
        </bpmndi:BPMNPlane>
    </bpmndi:BPMNDiagram>
</definitions>